[
  {
    "requestId": "REQ1774676743957",
    "name": "Ssss",
    "phone": "12112",
    "problem": "Health",
    "type": "Medical Emergency",
    "priority": "HIGH",
    "department": "Emergency Response Team",
    "response": "Contact nearest hospital and donor network immediately.",
    "status": "Completed"
  },
  {
    "requestId": "REQ1774677540195",
    "name": "Subha Mahadani",
    "phone": "7319873400",
    "problem": "I need medical help  have serious chest pain.",
    "type": "Medical Emergency",
    "priority": "HIGH",
    "department": "Emergency Response Team",
    "response": "Contact nearest hospital and donor network immediately.",
    "status": "Pending"
  }
]